hcclient/cli/cli.py
hcclient/client/client.py
hcclient/client/commands.py
hcclient/meta.py
hcclient/render/formatter.py
hcclient/utils/config.py
hcclient/utils/hook.py
hcclient-1.19.7.dist-info/LICENSE
hcclient-1.19.7.dist-info/METADATA
hcclient-1.19.7.dist-info/WHEEL
hcclient-1.19.7.dist-info/entry_points.txt
hcclient-1.19.7.dist-info/RECORD
