Metadata-Version: 2.1
Name: hcclient
Version: 1.19.7
Summary: A terminal client for connecting to hack.chat
Home-page: https://github.com/AnnikaV9/hcclient
License: Unlicense
Author: AnnikaV9
Author-email: carrot.moncher@gmail.com
Requires-Python: >=3.10,<4.0
Classifier: License :: OSI Approved
Classifier: Programming Language :: Python :: 3
Classifier: Programming Language :: Python :: 3.10
Classifier: Programming Language :: Python :: 3.11
Classifier: Programming Language :: Python :: 3.12
Classifier: Programming Language :: Python :: 3.13
Provides-Extra: latex
Requires-Dist: colorama (==0.4.6)
Requires-Dist: latex2sympy2 (==1.9.1) ; extra == "latex"
Requires-Dist: linkify-it-py (==2.0.3)
Requires-Dist: markdown-it-py (==3.0.0)
Requires-Dist: mdit-py-plugins (==0.4.2)
Requires-Dist: notify-py (==0.3.43)
Requires-Dist: packaging (==24.2)
Requires-Dist: prompt-toolkit (==3.0.48)
Requires-Dist: pygments (==2.18.0)
Requires-Dist: python-socks (==2.6.1)
Requires-Dist: pyyaml (==6.0.2)
Requires-Dist: termcolor (==2.5.0)
Requires-Dist: websocket-client (==1.8.0)
Requires-Dist: wsaccel (==0.6.7)
Project-URL: Repository, https://github.com/AnnikaV9/hcclient
